<?xml version="1.0" encoding="utf-8"?>
<data>
	<monster name="Nicitel">
		<visibleName>Nicitel</visibleName>
		<template>BasicMeleeCell</template>
		<stats> 
			<MaxHp>150</MaxHp>
			<MaxHp_scale>50</MaxHp_scale>
			<MaxSpeed>13</MaxSpeed>
			<IsAggressive>true</IsAggressive>
			<AggressionRange>15</AggressionRange>
			<RambleAround>true</RambleAround>
			<RambleAroundMaxDist>4</RambleAroundMaxDist>
			<AlertsAllies>true</AlertsAllies>

			<XpReward>3</XpReward>
		</stats>

		<add_autoattack>
			<MeleeAttack>
				<add_effect name="Pushaway" force="150"/>
			</MeleeAttack>
		</add_autoattack>

	</monster>

	<monster name="Healovac">
		<visibleName>DivnejHealer</visibleName>
		<template>HealerCell</template>

		<modify_skills>
			<HealBeam>
				<add_effect name="Pushaway" force="150"/>
			</HealBeam>
		</modify_skills>

		<add_skills>
			<CollisionDamageAttack>

			</CollisionDamageAttack>
		</add_skills>

	</monster>

	<monster name="Brutal">
		<visibleName>Brutalizator</visibleName>
		<template>CustomCell</template>
		<stats> 
			<MaxHp>50</MaxHp>
			<MaxHp_scale>10</MaxHp_scale>
			<MaxSpeed>10</MaxSpeed>
			<IsAggressive>true</IsAggressive>
			<AggressionRange>15</AggressionRange>
			<RambleAround>true</RambleAround>
			<RambleAroundMaxDist>4</RambleAroundMaxDist>
			<AlertsAllies>true</AlertsAllies>

			<XpReward>3</XpReward>
		</stats>

		<ai type="Melee">
			<set module="SpawnSkill" param="interval" value="5.4"/>
		</ai>

		<add_skills>
			<JumpShort>
				<reuse>1.0</reuse>
			</JumpShort>
		</add_skills>

		<add_skills>
			<CollisionDamageAttack>
				<add_effect name="HealSelf" value="10"/>
			</CollisionDamageAttack>
		</add_skills>
	</monster>

	<monster name="Hopak">
		<visibleName>Hopsan</visibleName>
		<template>SpiderCell</template>
		<stats> 
			<MaxSpeed>0</MaxSpeed>
		</stats>

		<ai type="Melee">
			<set module="EvasiveMovement" param="chanceEveryTick" value="0"/>

			<set module="JumpMovement" param="chanceEveryTick" value="100"/>
			<set module="JumpMovement" param="interval" value="2"/>
			<set module="JumpMovement" param="minRange" value="5"/>

			<set module="JumpSkill" param="enabled" value="false"/>
		</ai>

		<add_skills>
			<JumpShort>
				<reuse>0</reuse>
				<range>5</range>
			</JumpShort>
		</add_skills>
	</monster>
</data>